simo/__init__.py
simo/clustering.py
simo/evals.py
simo/helper.py
simo/regulation.py
simo/simo.py
simo/visualization.py
simo_omics-1.0.0.dist-info/LICENSE
simo_omics-1.0.0.dist-info/METADATA
simo_omics-1.0.0.dist-info/WHEEL
simo_omics-1.0.0.dist-info/top_level.txt
simo_omics-1.0.0.dist-info/RECORD
