Metadata-Version: 2.1
Name: simo-omics
Version: 1.0.0
Summary: SIMO: Spatial Integration of Multi-Omics single-cell datasets through probabilistic alignment
Home-page: https://github.com/ZJUFanLab/SIMO
Author: Penghui Yang
Author-email: yangph@zju.edu.cn
Classifier: Programming Language :: Python :: 3.8
Requires-Python: >=3.8
License-File: LICENSE
Requires-Dist: anndata (==0.9.2)
Requires-Dist: h5py (==3.10.0)
Requires-Dist: igraph (==0.10.8)
Requires-Dist: jupyterlab (==3.6.7)
Requires-Dist: kaleido (==0.2.1)
Requires-Dist: louvain (==0.7.1)
Requires-Dist: matplotlib (==3.5.2)
Requires-Dist: networkx (==3.1)
Requires-Dist: notebook (==6.3.0)
Requires-Dist: pot (==0.8.2)
Requires-Dist: numpy (==1.22.4)
Requires-Dist: pandas (==1.4.3)
Requires-Dist: PyComplexHeatmap (==1.6.7)
Requires-Dist: scikit-learn (==1.2.0)
Requires-Dist: scipy (==1.8.1)
Requires-Dist: scanpy (==1.9.1)
Requires-Dist: scikit-misc (==0.1.4)
Requires-Dist: leidenalg (==0.10.0)
